openinterview/__init__.py
openinterview/manager.py
openinterview/models/__init__.py
openinterview/models/claude.py
openinterview/models/gemini.py
openinterview/models/gpt.py
openinterview/modules/__init__.py
openinterview/modules/voice/__init__.py
openinterview/modules/voice/google.py
openinterview/modules/voice/openai.py
openinterview/modules/voice/random_play.py
openinterview/utils/__init__.py
openinterview/utils/doc_manager.py
openinterview/utils/file_manager.py
openinterview/utils/prompter.py
open_interview-1.0.13.dist-info/LICENSE
open_interview-1.0.13.dist-info/METADATA
open_interview-1.0.13.dist-info/WHEEL
open_interview-1.0.13.dist-info/top_level.txt
open_interview-1.0.13.dist-info/RECORD
