Metadata-Version: 2.1
Name: open-interview
Version: 1.0.13
Summary: The python package that returns Response of Google Gemini through API.
Home-page: https://github.com/dsdanielpark/open-interview
Author: Daniel Park
Author-email: parkminwoo1991@gmail.com
Keywords: Interview,LLM,ChatGPT,OpenAI,Claude,Anthropic
Classifier: Development Status :: 2 - Pre-Alpha
Classifier: Intended Audience :: Science/Research
Classifier: Natural Language :: English
Classifier: Programming Language :: Python
Classifier: Programming Language :: Python :: 3.7
Classifier: Programming Language :: Python :: 3.8
Classifier: Programming Language :: Python :: 3.9
Classifier: Programming Language :: Python :: 3.10
Classifier: Programming Language :: Python :: 3.11
Classifier: Programming Language :: Python :: 3.12
Classifier: License :: OSI Approved :: MIT License
Classifier: Topic :: Scientific/Engineering :: Artificial Intelligence
Requires-Python: >=3.7
License-File: LICENSE
Requires-Dist: openai ==0.28
Requires-Dist: anthropic
Requires-Dist: python-docx
Requires-Dist: utilfunction
Requires-Dist: python-gemini-api
Requires-Dist: lxml
Requires-Dist: gTTS
Requires-Dist: SpeechRecognition
Requires-Dist: PyPDF2
Requires-Dist: pygame
Provides-Extra: openaivoice
Requires-Dist: openai ; extra == 'openaivoice'
